topsis/__init__.py
topsis/__main__.py
Topsis_Twesha_102017195-0.0.2.dist-info/LICENSE
Topsis_Twesha_102017195-0.0.2.dist-info/METADATA
Topsis_Twesha_102017195-0.0.2.dist-info/WHEEL
Topsis_Twesha_102017195-0.0.2.dist-info/entry_points.txt
Topsis_Twesha_102017195-0.0.2.dist-info/top_level.txt
Topsis_Twesha_102017195-0.0.2.dist-info/RECORD
