Metadata-Version: 2.1
Name: Topsis-Twesha-102017195
Version: 0.0.2
Summary: Multi-Criteria Decision Making
Author: Twesha
License: MIT
Keywords: python,best model,Topsis,multi-criteria decision making,assignment
Classifier: Programming Language :: Python :: 3
Classifier: License :: OSI Approved :: MIT License
Classifier: Operating System :: OS Independent
License-File: LICENSE
Requires-Dist: pandas
